configcatclient/__init__.py
configcatclient/config.py
configcatclient/configcache.py
configcatclient/configcatclient.py
configcatclient/configcatoptions.py
configcatclient/configentry.py
configcatclient/configfetcher.py
configcatclient/configservice.py
configcatclient/datagovernance.py
configcatclient/evaluationcontext.py
configcatclient/evaluationdetails.py
configcatclient/evaluationlogbuilder.py
configcatclient/interfaces.py
configcatclient/localdictionarydatasource.py
configcatclient/localfiledatasource.py
configcatclient/logger.py
configcatclient/overridedatasource.py
configcatclient/pollingmode.py
configcatclient/py.typed
configcatclient/refreshresult.py
configcatclient/rolloutevaluator.py
configcatclient/user.py
configcatclient/utils.py
configcatclient/version.py
configcat_client-9.0.4.dist-info/LICENSE
configcat_client-9.0.4.dist-info/LICENSE.txt
configcat_client-9.0.4.dist-info/METADATA
configcat_client-9.0.4.dist-info/WHEEL
configcat_client-9.0.4.dist-info/top_level.txt
configcat_client-9.0.4.dist-info/RECORD
