Metadata-Version: 2.1
Name: configcat-client
Version: 9.0.4
Summary: ConfigCat SDK for Python. https://configcat.com
Home-page: https://github.com/configcat/python-sdk
Author: ConfigCat
Author-email: developer@configcat.com
License: MIT
Classifier: Intended Audience :: Developers
Classifier: License :: OSI Approved :: Apache Software License
Classifier: Operating System :: OS Independent
Classifier: Programming Language :: Python :: 2
Classifier: Programming Language :: Python :: 2.7
Classifier: Programming Language :: Python :: 3
Classifier: Programming Language :: Python :: 3.5
Classifier: Programming Language :: Python :: 3.6
Classifier: Programming Language :: Python :: 3.7
Classifier: Programming Language :: Python :: 3.8
Classifier: Programming Language :: Python :: 3.9
Classifier: Programming Language :: Python :: 3.10
Classifier: Programming Language :: Python :: 3.11
Classifier: Programming Language :: Python :: 3.12
Classifier: Topic :: Software Development
Classifier: Topic :: Software Development :: Libraries
License-File: LICENSE
License-File: LICENSE.txt
Requires-Dist: requests>=2.18.4; python_version < "3.7"
Requires-Dist: requests>=2.31.0; python_version >= "3.7"
Requires-Dist: semver>=2.10.2
Requires-Dist: enum-compat>=0.0.3
Requires-Dist: qualname>=0.1.0
Requires-Dist: pytz; python_version == "2.7"
